padmin/__init__.py
padmin/templates.py
padmin-0.0.1.dist-info/LICENSE
padmin-0.0.1.dist-info/METADATA
padmin-0.0.1.dist-info/WHEEL
padmin-0.0.1.dist-info/top_level.txt
padmin-0.0.1.dist-info/RECORD
